[
    {
        "id": "attack-claw1",
        "name": "Claw Attack",
        "desc": "swipe{!s} at {t} with their sharp claws",
        "tags": {
            "action": true,
            "attack": true
        },
        "stats": {
            "dmg-min": 1,
            "dmg-max": 4,
            "spd": 80
        }
    },
    {
        "id": "attack-tongue1",
        "name": "Tongue Smack",
        "desc": "smacks{!s} {t} with their tongue",
        "tags": {
            "action": true,
            "attack": true
        },
        "stats": {
            "dmg-min": 1,
            "dmg-max": 4,
            "spd": 80
        }
    },
    {
        "id": "attack-spit1",
        "name": "Acid Spit",
        "desc": "spit{!s} acid at {t}",
        "tags": {
            "action": true,
            "attack": true
        },
        "stats": {
            "dmg-min": 4,
            "dmg-max": 8,
            "spd": 120
        }
    }
]